mylib/__init__.py
mylib/mylib.py
mylibfahad-0.2.dist-info/METADATA
mylibfahad-0.2.dist-info/WHEEL
mylibfahad-0.2.dist-info/top_level.txt
mylibfahad-0.2.dist-info/RECORD
