Metadata-Version: 2.1
Name: mylibfahad
Version: 0.2
Summary: Testing to creat a library
Home-page: http://dont-have-link.com/no-link
Author: fahad.shawal
Author-email: fahadshawal@gmail.com
License: MIT
Platform: UNKNOWN
